ckanext_archiveview-0.0.2-py3.8-nspkg.pth
ckanext/archiveview/__init__.py
ckanext/archiveview/archive_util.py
ckanext/archiveview/plugin.py
ckanext/archiveview/logic/__init__.py
ckanext/archiveview/logic/action.py
ckanext/archiveview/tests/__init__.py
ckanext/archiveview/tests/archive_util_tests.py
ckanext_archiveview-0.0.2.dist-info/LICENSE
ckanext_archiveview-0.0.2.dist-info/METADATA
ckanext_archiveview-0.0.2.dist-info/WHEEL
ckanext_archiveview-0.0.2.dist-info/entry_points.txt
ckanext_archiveview-0.0.2.dist-info/namespace_packages.txt
ckanext_archiveview-0.0.2.dist-info/top_level.txt
ckanext_archiveview-0.0.2.dist-info/RECORD
