Metadata-Version: 2.1
Name: ckanext-archiveview
Version: 0.0.2
Summary: A ckan extension that provides a resource view for zipped archives.
Home-page: https://github.com/fwoerister/ckanext-archiveview
Author: Florian Woerister
Author-email: florian.woerister@tuwien.ac.at
License: AGPLv3+
Keywords: CKAN archive zip
Platform: UNKNOWN
Classifier: Development Status :: 4 - Beta
Classifier: License :: OSI Approved :: GNU Affero General Public License v3 or later (AGPLv3+)
Classifier: Programming Language :: Python :: 3
